devghost/__init__.py
devghost/cli.py
devghost-0.1.0.dist-info/METADATA
devghost-0.1.0.dist-info/WHEEL
devghost-0.1.0.dist-info/entry_points.txt
devghost-0.1.0.dist-info/top_level.txt
devghost-0.1.0.dist-info/RECORD
