Metadata-Version: 2.4
Name: devghost
Version: 0.1.0
Summary: DevGhost: Smart CLI for AI-powered commit messages
Home-page: https://github.com/yourusername/devghost
Author: Your Name
Classifier: Programming Language :: Python :: 3
Classifier: License :: OSI Approved :: MIT License
Classifier: Operating System :: OS Independent
Requires-Python: >=3.7
Requires-Dist: click
Requires-Dist: requests
Requires-Dist: PyGithub
Dynamic: author
Dynamic: classifier
Dynamic: description
Dynamic: description-content-type
Dynamic: home-page
Dynamic: requires-dist
Dynamic: requires-python
Dynamic: summary
